bigquery_exporter/__init__.py
bigquery_exporter/base.py
bigquery_exporter/constants.py
bigquery_exporter/errors.py
bigquery_exporter/helpers.py
bigquery_exporter/clients/__init__.py
bigquery_exporter/clients/google_client.py
bigquery_exporter/clients/interface.py
django_bigquery_exporter-0.2.4.dist-info/licenses/LICENSE
tests/__init__.py
tests/conftest.py
tests/test_base.py
tests/test_client.py
django_bigquery_exporter-0.2.4.dist-info/METADATA
django_bigquery_exporter-0.2.4.dist-info/WHEEL
django_bigquery_exporter-0.2.4.dist-info/top_level.txt
django_bigquery_exporter-0.2.4.dist-info/RECORD
