Metadata-Version: 2.4
Name: django-bigquery-exporter
Version: 0.2.4
Summary: A Django plugin for exporting CMS data to Google BigQuery.
Home-page: https://www.industrydive.com/
Author: Dave Frame
Author-email: dframe22@gmail.com
License: MIT License
Classifier: Environment :: Web Environment
Classifier: Framework :: Django
Classifier: Framework :: Django :: 3.2
Classifier: Intended Audience :: Developers
Classifier: License :: OSI Approved :: BSD License
Classifier: Operating System :: OS Independent
Classifier: Programming Language :: Python
Classifier: Programming Language :: Python :: 3
Classifier: Programming Language :: Python :: 3 :: Only
Classifier: Programming Language :: Python :: 3.8
Classifier: Programming Language :: Python :: 3.9
Classifier: Topic :: Internet :: WWW/HTTP
Classifier: Topic :: Internet :: WWW/HTTP :: Dynamic Content
Requires-Python: >=3.8
License-File: LICENSE
Requires-Dist: Django>=3.2.4
Requires-Dist: google-auth>=1.32.1
Requires-Dist: google-cloud-bigquery>=2.30.1
Requires-Dist: pytz>=2019.1
Dynamic: license-file
Dynamic: requires-dist
